vibebash/__init__.py
vibebash/main.py
vibebash-1.0.1.dist-info/METADATA
vibebash-1.0.1.dist-info/WHEEL
vibebash-1.0.1.dist-info/entry_points.txt
vibebash-1.0.1.dist-info/licenses/LICENSE
vibebash-1.0.1.dist-info/RECORD
