Metadata-Version: 2.4
Name: vibebash
Version: 1.0.1
Summary: Natural language to shell commands with AI - Interactive CLI tool
Project-URL: Homepage, https://github.com/yourusername/vibebash
Project-URL: Documentation, https://github.com/yourusername/vibebash#readme
Project-URL: Repository, https://github.com/yourusername/vibebash.git
Project-URL: Issues, https://github.com/yourusername/vibebash/issues
Project-URL: Changelog, https://github.com/yourusername/vibebash/releases
Author-email: Binh Pham <binhpham@binhph.am>
License-Expression: MIT
License-File: LICENSE
Keywords: ai,automation,cli,commands,llm,natural-language,shell,terminal
Classifier: Development Status :: 4 - Beta
Classifier: Environment :: Console
Classifier: Intended Audience :: Developers
Classifier: License :: OSI Approved :: MIT License
Classifier: Operating System :: OS Independent
Classifier: Programming Language :: Python :: 3
Classifier: Programming Language :: Python :: 3.8
Classifier: Programming Language :: Python :: 3.9
Classifier: Programming Language :: Python :: 3.10
Classifier: Programming Language :: Python :: 3.11
Classifier: Programming Language :: Python :: 3.12
Classifier: Topic :: Software Development :: Libraries :: Python Modules
Classifier: Topic :: System :: Shells
Classifier: Topic :: Utilities
Requires-Python: >=3.8
Requires-Dist: click>=8.0.0
Requires-Dist: langchain-ollama>=0.1.0
Requires-Dist: langchain>=0.0.350
Requires-Dist: pydantic>=2.0.0
Requires-Dist: rich>=13.0.0
Provides-Extra: all
Requires-Dist: black>=23.0.0; extra == 'all'
Requires-Dist: flake8>=6.0.0; extra == 'all'
Requires-Dist: mypy>=1.0.0; extra == 'all'
Requires-Dist: pre-commit>=3.0.0; extra == 'all'
Requires-Dist: pytest-asyncio>=0.21.0; extra == 'all'
Requires-Dist: pytest-cov>=4.0.0; extra == 'all'
Requires-Dist: pytest-mock>=3.10.0; extra == 'all'
Requires-Dist: pytest>=7.0.0; extra == 'all'
Requires-Dist: requests>=2.28.0; extra == 'all'
Provides-Extra: dev
Requires-Dist: black>=23.0.0; extra == 'dev'
Requires-Dist: flake8>=6.0.0; extra == 'dev'
Requires-Dist: mypy>=1.0.0; extra == 'dev'
Requires-Dist: pre-commit>=3.0.0; extra == 'dev'
Requires-Dist: pytest-asyncio>=0.21.0; extra == 'dev'
Requires-Dist: pytest-cov>=4.0.0; extra == 'dev'
Requires-Dist: pytest-mock>=3.10.0; extra == 'dev'
Requires-Dist: pytest>=7.0.0; extra == 'dev'
Provides-Extra: test
Requires-Dist: pytest-asyncio>=0.21.0; extra == 'test'
Requires-Dist: pytest-cov>=4.0.0; extra == 'test'
Requires-Dist: pytest-mock>=3.10.0; extra == 'test'
Requires-Dist: pytest>=7.0.0; extra == 'test'
Requires-Dist: requests>=2.28.0; extra == 'test'
